MANIFEST.in
README.rst
requirements-development.txt
requirements.txt
setup.py
mongoengine_embedded/__init__.py
mongoengine_embedded/__version__.py
mongoengine_embedded/embedded_resource.py
mongoengine_embedded.egg-info/PKG-INFO
mongoengine_embedded.egg-info/SOURCES.txt
mongoengine_embedded.egg-info/dependency_links.txt
mongoengine_embedded.egg-info/not-zip-safe
mongoengine_embedded.egg-info/requires.txt
mongoengine_embedded.egg-info/top_level.txt
mongoengine_embedded/resource_container/__init__.py
mongoengine_embedded/resource_container/resource_container.py