Metadata-Version: 1.0
Name: mongoengine-embedded
Version: 1.0.1
Summary: Access embedded documents with CRUD by id.
Home-page: https://github.com/karloku/mongoengine-embedded
Author: Karloku Sang
Author-email: karloku@loku.it
License: MIT
Platform: UNKNOWN
